Metadata-Version: 1.0
Name: django-userel
Version: 0.0.2
Summary: Extend ForeignKey field for User. It support ``auto_now`` and ``auto_now_add``
Home-page: https://github.com/lambdalisue/django-userel
Author: Alisue
Author-email: lambdalisue@hashnote.net
License: MIT
Download-URL: https://github.com/lambdalisue/django-userel/tarball/master
Keywords: django ForeignKey auto_now auto_now_add user
Platform: UNKNOWN
Classifier: Framework :: Django
Classifier: Intended Audience :: Developers
Classifier: License :: OSI Approved :: MIT License
Classifier: Programming Language :: Python
Classifier: Topic :: Internet :: WWW/HTTP
